Workbook
Name BudgetTotal: '0. Profil'!$C$17
Name CBTP_PV: '12. Disbursement Monitoring'!$C$23
Name CRTR_AC: '12. Disbursement Monitoring'!$E$23
Name EAC_Estimation: '13. Dashboard'!$C$15
Name IPC_CPI: '13. Dashboard'!$C$12
Name IPE_SPI: '13. Dashboard'!$C$14
Name PctTravail: '13. Dashboard'!$C$9
Name VAC_Variance: '13. Dashboard'!$C$16

Sheet MENU fr
A1: 🏗️ OUTIL DE PILOTAGE PMO — SUIVI & ÉVALUATION
A5: ='0. Profil'!C5 -> 0 | H5: ='0. Profil'!C7 -> 0 | O5: =TODAY() -> 46186
B7: 📋 0. PROFIL DU PROJET | H7: 🌍 1. ANALYSE ENVIRONNEMENT | N7: 👥 2. PARTIES PRENANTES
B10: 🗂️ 3. CADRE LOGIQUE | H10: ❓ 4. QUESTIONS PERFORMANCE | N10: ⚠️ 5. GESTION DES RISQUES
B13: 📊 6. SÉLECTION INDICATEURS | H13: 📈 7. INDICATEURS EFFICACITÉ | N13: 📄 8. FICHE INDICATEURS
B16: 📅 9. CALENDRIER INDICATEURS | H16: 🗃️ 10. COLLECTE DE DONNÉES | N16: 🔍 11. MATRICE S&E
B19: 💰 12. SUIVI DÉCAISSEMENTS | H19: 🎯 TABLEAU DE BORD | N19: 📝 14. RAPPORT D'AVANCEMENT
B22: 🏆 15. MATRICE D'ÉVALUATION | H22: 🛒 16. PLAN PASSATION MARCHÉS
A25: 💰 IPC | E25: ='13. Dashboard'!C12 -> 0 | H25: 📅 IPE | L25: ='13. Dashboard'!C14 -> 0 | O25: 🎯 EAC Estimé | S25: ='13. Dashboard'!C29 -> 🔴 ROUGE

Sheet HOME
A1: GUIDE D'UTILISATION — OUTIL PMO
A2: ⬅ MENU
A4: ÉTAPE | B4: ONGLET | C4: DESCRIPTION
A5: 0 | B5: Profil du Projet | C5: Saisir les informations de base du projet (titre, responsable, budget, dates)
A6: 1 | B6: Analyse Environnement | C6: Identifier les facteurs externes pouvant impacter le projet
A7: 2 | B7: Parties Prenantes | C7: Recenser et analyser les acteurs clés
A8: 3 | B8: Cadre Logique | C8: Structurer la logique d'intervention (MCL)
A9: 4 | B9: Questions Performance | C9: Définir les questions d'évaluation par niveau de résultats
A10: 5 | B10: Gestion des Risques | C10: Identifier, scorer et planifier la mitigation des risques
A11: 6 | B11: Sélection Indicateurs | C11: Évaluer et sélectionner les indicateurs SMARTIES
A12: 7 | B12: Indicateurs Efficacité | C12: Documenter les indicateurs d'efficience et efficacité
A13: 8 | B13: Fiche Indicateurs | C13: Décrire chaque indicateur en détail (baseline, cibles, sources)
A14: 9 | B14: Calendrier Indicateurs | C14: Planifier les valeurs cibles par trimestre sur 5 ans
A15: 10 | B15: Collecte de Données | C15: Définir les mécanismes de collecte
... A21: 16 | B21: Plan Passation Marchés | C21: Suivre les processus d'acquisition
A24: 📊 INDICATEURS EN TEMPS RÉEL
A25: IPC — Indice Coûts | C25: ='13. Dashboard'!C12 -> 0
A26: IPE — Indice Calendrier | C26: ='13. Dashboard'!C14 -> 0
A27: EAC — Estimé Achèvement | C27: ='13. Dashboard'!C15
A28: STATUT GLOBAL | C28: ='13. Dashboard'!C22 -> 0

Sheet 0. Profil
A1: PROFIL DU PROJET
A2: ⬅ MENU
A4: INFORMATIONS GÉNÉRALES DU PROJET
A5: Titre du Projet
A6: No du Projet / Code
A7: Responsable / Chef de Projet
A8: Unité de Gestion
A9: Pays
A10: Secteur
A11: Thème
A12: Date de début
A13: Date de fin
A14: Durée totale (mois) | C14: =IFERROR(DATEDIF(C12,C13,"M"),"") -> 0
A15: Agence de financement
A16: Agence principale
A17: Budget Total (FCFA)
A19: OBJECTIFS ET DESCRIPTION DU PROJET
A20: Objectifs du projet
A22: Composantes principales
A24: Description du projet

Sheet 1. Environment
A1: ANALYSE DE L'ENVIRONNEMENT
A2: ⬅ MENU
A3: Projet : | D3: ='0. Profil'!C5 -> 0
A4: DIMENSIONS ENVIRONNEMENTALES DU PROJET (PESTEL)
A5: Dimension | B5: Paramètre principal | C5: Parties Prenantes concernées | D5: Opportunités | E5: Risques

Sheet 2. Stakeholders
A1: ANALYSE DES PARTIES PRENANTES
A2: ⬅ MENU
A3: Projet : | D3: ='0. Profil'!C5 -> 0
A4: IDENTIFICATION ET STRATÉGIE — PARTIES PRENANTES
A5: No | B5: Parties Prenantes | C5: Objectifs / Intérêts | D5: Pouvoir / Importance | E5: Action potentielle (+/-) | F5: Stratégie à implanter | G5: Action à prendre | H5: Priorité

Sheet 3. Logical Framework
A1: CADRE LOGIQUE (MCL)
A2: ⬅ MENU
A3: Projet : | D3: ='0. Profil'!C5 -> 0
A4: MATRICE DU CADRE LOGIQUE
A5: NARRATIF DU PROJET (Paramètres) | B5: INDICATEURS DE RÉSULTATS (IOV) | C5: MOYENS DE VÉRIFICATION | D5: SUPPOSITION CRITIQUE | E5: NIVEAU
A6: OBJECTIF DU PROGRAMME (Impact)
A10: OBJECTIF DU PROJET (Effet)
A14: EXTRANTS
A18: INTRANTS

Sheet 4. Performance Questions
A1: QUESTIONS DE PERFORMANCE
A2: ⬅ MENU
A3: Projet : | D3: ='0. Profil'!C5 -> 0
A4: CHAÎNE DE RÉSULTATS — PARTIES PRENANTES — QUESTIONS DE PERFORMANCE
A5: Chaîne de résultats | B5: Parties Prenantes | C5: Questions de Performance | D5: Indicateurs associés

Sheet 5. Risks Analysis
A1: GESTION & ANALYSE DES RISQUES
A2: ⬅ MENU
A3: Projet : | D3: ='0. Profil'!C5 -> 0
A5: REGISTRE DES RISQUES — MATRICE DE SCORING
A6: ID | B6: DESCRIPTION DU RISQUE | C6: CATÉGORIE | D6: PROBABILITÉ (1-5) | E6: IMPACT (1-5) | F6: SCORE (P × I) | G6: NIVEAU | H6: STRATÉGIE DE MITIGATION | I6: RESPONSABLE | J6: FRÉQUENCE | K6: STATUT
A7: 1 | B7: Dépassement budget composante 1 | C7: Financier | D7: 4 | E7: 5 | F7: =IFERROR(IF(AND(D7<>"",E7<>""),D7*E7,""),"") -> 20 | G7: =IFERROR(IF(F7="","",IF(F7>=16,"🔴 CRITIQUE",IF(F7>=9,"🟠 ÉLEVÉ",IF(F7>=4,"🟡 MODÉRÉ","🟢 FAIBLE")))),"" ) -> 🔴 CRITIQUE
A8: 2 | B8: Retard livraisons équipements | C8: Technique | D8: 3 | E8: 4 | F8: =IFERROR(IF(AND(D8<>"",E8<>""),D8*E8,""),"") -> 12 | G8: =IFERROR(IF(F8="","",IF(F8>=16,"🔴 CRITIQUE",IF(F8>=9,"🟠 ÉLEVÉ",IF(F8>=4,"🟡 MODÉRÉ","🟢 FAIBLE")))),"" ) -> 🟠 ÉLEVÉ
A9: 3 | B9: Rotation élevée du personnel | C9: Organisationnel | D9: 3 | E9: 3 | F9: =IFERROR(IF(AND(D9<>"",E9<>""),D9*E9,""),"") -> 9 | G9: =IFERROR(IF(F9="","",IF(F9>=16,"🔴 CRITIQUE",IF(F9>=9,"🟠 ÉLEVÉ",IF(F9>=4,"🟡 MODÉRÉ","🟢 FAIBLE")))),"" ) -> 🟠 ÉLEVÉ
A10: 4 | B10: Inondations saisonnières | C10: Environnemental | D10: 2 | E10: 4 | F10: =IFERROR(IF(AND(D10<>"",E10<>""),D10*E10,""),"") -> 8 | G10: =IFERROR(IF(F10="","",IF(F10>=16,"🔴 CRITIQUE",IF(F10>=9,"🟠 ÉLEVÉ",IF(F10>=4,"🟡 MODÉRÉ","🟢 FAIBLE")))),"" ) -> 🟡 MODÉRÉ
A11: 5 | B11: Changement politique fiscal | C11: Politique | D11: 2 | E11: 3 | F11: =IFERROR(IF(AND(D11<>"",E11<>""),D11*E11,""),"") -> 6 | G11: =IFERROR(IF(F11="","",IF(F11>=16,"🔴 CRITIQUE",IF(F11>=9,"🟠 ÉLEVÉ",IF(F11>=4,"🟡 MODÉRÉ","🟢 FAIBLE")))),"" ) -> 🟡 MODÉRÉ
A12: 6 | B12: Résistance communautaire | C12: Social | D12: 2 | E12: 2 | F12: =IFERROR(IF(AND(D12<>"",E12<>""),D12*E12,""),"") -> 4 | G12: =IFERROR(IF(F12="","",IF(F12>=16,"🔴 CRITIQUE",IF(F12>=9,"🟠 ÉLEVÉ",IF(F12>=4,"🟡 MODÉRÉ","🟢 FAIBLE")))),"" ) -> 🟡 MODÉRÉ
A13: 7 | B13: Panne système informatique | C13: Technique | D13: 3 | E13: 3 | F13: =IFERROR(IF(AND(D13<>"",E13<>""),D13*E13,""),"") -> 9 | G13: =IFERROR(IF(F13="","",IF(F13>=16,"🔴 CRITIQUE",IF(F13>=9,"🟠 ÉLEVÉ",IF(F13>=4,"🟡 MODÉRÉ","🟢 FAIBLE")))),"" ) -> 🟠 ÉLEVÉ
A14: 8 | B14: Délais validation administrative | C14: Organisationnel | D14: 4 | E14: 3 | F14: =IFERROR(IF(AND(D14<>"",E14<>""),D14*E14,""),"") -> 12 | G14: =IFERROR(IF(F14="","",IF(F14>=16,"🔴 CRITIQUE",IF(F14>=9,"🟠 ÉLEVÉ",IF(F14>=4,"🟡 MODÉRÉ","🟢 FAIBLE")))),"" ) -> 🟠 ÉLEVÉ
A15: 9 | B15: Fluctuation taux de change | C15: Financier | D15: 3 | E15: 4 | F15: =IFERROR(IF(AND(D15<>"",E15<>""),D15*E15,""),"") -> 12 | G15: =IFERROR(IF(F15="","",IF(F15>=16,"🔴 CRITIQUE",IF(F15>=9,"🟠 ÉLEVÉ",IF(F15>=4,"🟡 MODÉRÉ","🟢 FAIBLE")))),"" ) -> 🟠 ÉLEVÉ
A16: 10 | B16: Risque sécuritaire zone d'intervention | C16: Autre | D16: 2 | E16: 5 | F16: =IFERROR(IF(AND(D16<>"",E16<>""),D16*E16,""),"") -> 10 | G16: =IFERROR(IF(F16="","",IF(F16>=16,"🔴 CRITIQUE",IF(F16>=9,"🟠 ÉLEVÉ",IF(F16>=4,"🟡 MODÉRÉ","🟢 FAIBLE")))),"" ) -> 🟠 ÉLEVÉ
A18: SYNTHÈSE — TABLEAU DE BORD RISQUES
A19: Nb risques CRITIQUES (score ≥ 16) | H19: =COUNTIF(F7:F16,">=16") -> 1
A20: Nb risques ÉLEVÉS (9 ≤ score < 16) | H20: =COUNTIFS(F7:F16,">=9",F7:F16,"<16") -> 6
A21: Nb risques MODÉRÉS (4 ≤ score < 9) | H21: =COUNTIFS(F7:F16,">=4",F7:F16,"<9") -> 3
A22: Nb risques FAIBLES (score < 4) | H22: =COUNTIF(F7:F16,"<4") -> 0
A23: Score moyen global | H23: =IFERROR(AVERAGEIF(F7:F16,"<>"),0) -> 10.2
A24: Risque le plus critique (description) | H24: =IFERROR(INDEX(B7:B16,MATCH(MAX(F7:F16),F7:F16,0)),"—") -> Dépassement budget composante 1
M26: DONNÉES RADAR — Score par Catégorie
M27: Catégorie | N27: Score Moyen
M28: Financier | N28: =IFERROR(AVERAGEIFS($F$7:$F$16,$C$7:$C$16,M28),0) -> 16
M29: Technique | N29: =IFERROR(AVERAGEIFS($F$7:$F$16,$C$7:$C$16,M29),0) -> 10.5
M30: Organisationnel | N30: =IFERROR(AVERAGEIFS($F$7:$F$16,$C$7:$C$16,M30),0) -> 10.5
M31: Environnemental | N31: =IFERROR(AVERAGEIFS($F$7:$F$16,$C$7:$C$16,M31),0) -> 8
M32: Politique | N32: =IFERROR(AVERAGEIFS($F$7:$F$16,$C$7:$C$16,M32),0) -> 6
M33: Social | N33: =IFERROR(AVERAGEIFS($F$7:$F$16,$C$7:$C$16,M33),0) -> 4
M34: Autre | N34: =IFERROR(AVERAGEIFS($F$7:$F$16,$C$7:$C$16,M34),0) -> 10

Sheet 6. Indicators selection
A1: SÉLECTION D'INDICATEURS — CRITÈRES SMARTIES
A2: ⬅ MENU
A3: Projet : | D3: ='0. Profil'!C5 -> 0
A4: GRILLE D'ÉVALUATION SMARTIES (Score 1-5 par critère)
A5: Catégorie | B5: Indicateur | C5: S | D5: M | E5: A | F5: R | G5: T | H5: I | I5: E | J5: S | K5: Score (%) | L5: Seuil | M5: Choix | O5: DONNÉES RADAR SMARTIES | Q5: Max
A6: Légende : 1 = Très faible → 5 = Très élevé. Score % = Somme/(8×5). Choix si Score % > 60% | O6: Critère | P6: Moy. /5
A7: Impact | B7: Indicateur 1 | C7: 4 | D7: 5 | E7: 4 | F7: 3 | G7: 4 | H7: 2 | I7: 3 | J7: 2 | K7: =IFERROR((C7+D7+E7+F7+G7+H7+I7+J7)/(8*5),"") -> 0.675 | L7: 0.6 | M7: =IFERROR(IF(K7>=0.6,"✅ RETENU","❌ Écarter"),"—") -> ✅ RETENU | O7: S — Spécifique | P7: =IFERROR(AVERAGEIF(C7:C26,"<>"&""),0) -> 3.5 | Q7: 5
B8: Indicateur 2 | C8: 3 | D8: 4 | E8: 3 | F8: 2 | G8: 3 | H8: 1 | I8: 2 | J8: 1 | K8: =IFERROR((C8+D8+E8+F8+G8+H8+I8+J8)/(8*5),"") -> 0.475 | L8: 0.6 | M8: =IFERROR(IF(K8>=0.6,"✅ RETENU","❌ Écarter"),"—") -> ❌ Écarter | O8: M — Mesurable | P8: =IFERROR(AVERAGEIF(D7:D26,"<>"&""),0) -> 4.5 | Q8: 5
B9: Indicateur 3 | K9: =IFERROR((C9+D9+E9+F9+G9+H9+I9+J9)/(8*5),"") -> 0 | L9: 0.6 | M9: =IFERROR(IF(K9>=0.6,"✅ RETENU","❌ Écarter"),"—") -> ❌ Écarter | O9: A — Atteignable | P9: =IFERROR(AVERAGEIF(E7:E26,"<>"&""),0) -> 3.5 | Q9: 5
A10: Effet | B10: Indicateur 1 | C10: 4 | D10: 5 | E10: 4 | F10: 3 | G10: 4 | H10: 2 | I10: 3 | J10: 2 | K10: =IFERROR((C10+D10+E10+F10+G10+H10+I10+J10)/(8*5),"") -> 0.675 | L10: 0.6 | M10: =IFERROR(IF(K10>=0.6,"✅ RETENU","❌ Écarter"),"—") -> ✅ RETENU | O10: R — Réaliste | P10: =IFERROR(AVERAGEIF(F7:F26,"<>"&""),0) -> 2.5 | Q10: 5
B11: Indicateur 2 | C11: 3 | D11: 4 | E11: 3 | F11: 2 | G11: 3 | H11: 1 | I11: 2 | J11: 1 | K11: =IFERROR((C11+D11+E11+F11+G11+H11+I11+J11)/(8*5),"") -> 0.475 | L11: 0.6 | M11: =IFERROR(IF(K11>=0.6,"✅ RETENU","❌ Écarter"),"—") -> ❌ Écarter | O11: T — Temporel | P11: =IFERROR(AVERAGEIF(G7:G26,"<>"&""),0) -> 3.5 | Q11: 5
B12: Indicateur 3 | K12: =IFERROR((C12+D12+E12+F12+G12+H12+I12+J12)/(8*5),"") -> 0 | L12: 0.6 | M12: =IFERROR(IF(K12>=0.6,"✅ RETENU","❌ Écarter"),"—") -> ❌ Écarter | O12: I — Indépendant | P12: =IFERROR(AVERAGEIF(H7:H26,"<>"&""),0) -> 1.5 | Q12: 5
B13: Indicateur 4 | K13: =IFERROR((C13+D13+E13+F13+G13+H13+I13+J13)/(8*5),"") -> 0 | L13: 0.6 | M13: =IFERROR(IF(K13>=0.6,"✅ RETENU","❌ Écarter"),"—") -> ❌ Écarter | O13: E — Éthique | P13: =IFERROR(AVERAGEIF(I7:I26,"<>"&""),0) -> 2.5 | Q13: 5
B14: Indicateur 5 | K14: =IFERROR((C14+D14+E14+F14+G14+H14+I14+J14)/(8*5),"") -> 0 | L14: 0.6 | M14: =IFERROR(IF(K14>=0.6,"✅ RETENU","❌ Écarter"),"—") -> ❌ Écarter | O14: S — Sensible genre | P14: =IFERROR(AVERAGEIF(J7:J26,"<>"&""),0) -> 1.5 | Q14: 5
A15: Extrants | B15: Indicateur 1 | K15: =IFERROR((C15+D15+E15+F15+G15+H15+I15+J15)/(8*5),"") -> 0 | L15: 0.6 | M15: =IFERROR(IF(K15>=0.6,"✅ RETENU","❌ Écarter"),"—") -> ❌ Écarter
B16: Indicateur 2 | K16: =IFERROR((C16+D16+E16+F16+G16+H16+I16+J16)/(8*5),"") -> 0 | L16: 0.6 | M16: =IFERROR(IF(K16>=0.6,"✅ RETENU","❌ Écarter"),"—") -> ❌ Écarter
B17: Indicateur 3 | K17: =IFERROR((C17+D17+E17+F17+G17+H17+I17+J17)/(8*5),"") -> 0 | L17: 0.6 | M17: =IFERROR(IF(K17>=0.6,"✅ RETENU","❌ Écarter"),"—") -> ❌ Écarter
B18: Indicateur 4 | K18: =IFERROR((C18+D18+E18+F18+G18+H18+I18+J18)/(8*5),"") -> 0 | L18: 0.6 | M18: =IFERROR(IF(K18>=0.6,"✅ RETENU","❌ Écarter"),"—") -> ❌ Écarter
B19: Indicateur 5 | K19: =IFERROR((C19+D19+E19+F19+G19+H19+I19+J19)/(8*5),"") -> 0 | L19: 0.6 | M19: =IFERROR(IF(K19>=0.6,"✅ RETENU","❌ Écarter"),"—") -> ❌ Écarter
B20: Indicateur 6 | K20: =IFERROR((C20+D20+E20+F20+G20+H20+I20+J20)/(8*5),"") -> 0 | L20: 0.6 | M20: =IFERROR(IF(K20>=0.6,"✅ RETENU","❌ Écarter"),"—") -> ❌ Écarter
A21: Intrants | B21: Indicateur 1 | K21: =IFERROR((C21+D21+E21+F21+G21+H21+I21+J21)/(8*5),"") -> 0 | L21: 0.6 | M21: =IFERROR(IF(K21>=0.6,"✅ RETENU","❌ Écarter"),"—") -> ❌ Écarter
B22: Indicateur 2 | K22: =IFERROR((C22+D22+E22+F22+G22+H22+I22+J22)/(8*5),"") -> 0 | L22: 0.6 | M22: =IFERROR(IF(K22>=0.6,"✅ RETENU","❌ Écarter"),"—") -> ❌ Écarter
B23: Indicateur 3 | K23: =IFERROR((C23+D23+E23+F23+G23+H23+I23+J23)/(8*5),"") -> 0 | L23: 0.6 | M23: =IFERROR(IF(K23>=0.6,"✅ RETENU","❌ Écarter"),"—") -> ❌ Écarter
B24: Indicateur 4 | K24: =IFERROR((C24+D24+E24+F24+G24+H24+I24+J24)/(8*5),"") -> 0 | L24: 0.6 | M24: =IFERROR(IF(K24>=0.6,"✅ RETENU","❌ Écarter"),"—") -> ❌ Écarter
B25: Indicateur 5 | K25: =IFERROR((C25+D25+E25+F25+G25+H25+I25+J25)/(8*5),"") -> 0 | L25: 0.6 | M25: =IFERROR(IF(K25>=0.6,"✅ RETENU","❌ Écarter"),"—") -> ❌ Écarter
B26: Indicateur 6 | K26: =IFERROR((C26+D26+E26+F26+G26+H26+I26+J26)/(8*5),"") -> 0 | L26: 0.6 | M26: =IFERROR(IF(K26>=0.6,"✅ RETENU","❌ Écarter"),"—") -> ❌ Écarter

Sheet 7. Efficacy indicators
A1: INDICATEURS D'EFFICACITÉ
A2: ⬅ MENU
A3: Projet : | D3: ='0. Profil'!C5 -> 0
A4: CHAÎNE DES RÉSULTATS — INDICATEURS D'EFFICIENCE & EFFICACITÉ
A5: Narratif du Projet (Paramètres) | B5: Indicateurs de Résultats (IOV) | C5: Indicateurs de Risque | D5: Indicateur d'Efficacité | E5: Fréquence | F5: Responsable

Sheet 8. Indicators files
A1: FICHE D'INDICATEURS
A2: ⬅ MENU
A3: Projet : | D3: ='0. Profil'!C5 -> 0
A4: DOCUMENTATION DÉTAILLÉE DES INDICATEURS
A5: Nom de l'indicateur | B5: Objectif lié | C5: Niveau | D5: Définition | E5: Baseline | F5: Cible finale | G5: Unité | H5: Source de vérification | I5: Fréquence | J5: Responsable | K5: Méthode collecte

Sheet 9. Indicators Calendar
A1: CALENDRIER DES INDICATEURS — SUIVI TRIMESTRIEL 5 ANS
A2: ⬅ MENU
A4: Calendrier de suivi | E4: Année 1 | I4: Année 2 | M4: Année 3 | Q4: Année 4 | U4: Année 5
B5: RÉSULTATS | C5: Indicateur | D5: Type/Données | E5: Q1 | F5: Q2 | G5: Q3 | H5: Q4 | I5: Q1 | J5: Q2 | K5: Q3 | L5: Q4 | M5: Q1 | N5: Q2 | O5: Q3 | P5: Q4 | Q5: Q1 | R5: Q2 | S5: Q3 | T5: Q4 | U5: Q1 | V5: Q2 | W5: Q3 | X5: Q4
A6: IMPACT | B6: Indicateur IMP.1 | C6: Unité / fréquence | D6: Cible | E6: 10 | F6: 20 | G6: 30 | H6: 40 | I6: 55 | J6: 65 | K6: 75 | L6: 85 | M6: 90 | N6: 92 | O6: 94 | P6: 96 | Q6: 97 | R6: 98 | S6: 99 | T6: 100 | U6: 100 | V6: 100 | W6: 100 | X6: 100
D7: Réel | E7: 8 | F7: 17 | G7: 26 | H7: 35 | I7: 45 | J7: 52 | K7: 60
D8: Déviation | E8: =IFERROR(IF(AND(E7<>"",E6<>""),E7-E6,""),"") -> -2 | F8: =IFERROR(IF(AND(F7<>"",F6<>""),F7-F6,""),"") -> -3 | G8: =IFERROR(IF(AND(G7<>"",G6<>""),G7-G6,""),"") -> -4 | H8: =IFERROR(IF(AND(H7<>"",H6<>""),H7-H6,""),"") -> -5 | I8: =IFERROR(IF(AND(I7<>"",I6<>""),I7-I6,""),"") -> -10 | J8: =IFERROR(IF(AND(J7<>"",J6<>""),J7-J6,""),"") -> -13 | K8: =IFERROR(IF(AND(K7<>"",K6<>""),K7-K6,""),"") -> -15 | L8: =IFERROR(IF(AND(L7<>"",L6<>""),L7-L6,""),"") | ... X8: =IFERROR(IF(AND(X7<>"",X6<>""),X7-X6,""),"")
D9: Commentaires
A11: EFFET | B11: Indicateur EFF.1 | C11: Unité / fréquence | D11: Cible | E11: 5 | F11: 12 | G11: 22 | H11: 35 | I11: 48 | J11: 60 | K11: 72 | L11: 82 | M11: 88 | N11: 91 | O11: 93 | P11: 95 | Q11: 97 | R11: 98 | S11: 99 | T11: 100 | U11: 100 | V11: 100 | W11: 100 | X11: 100
D12: Réel | E12: 4 | F12: 10 | G12: 18 | H12: 28 | I12: 40 | J12: 50 | K12: 58
D13: Déviation | E13: =IFERROR(IF(AND(E12<>"",E11<>""),E12-E11,""),"") -> -1 | F13: =IFERROR(IF(AND(F12<>"",F11<>""),F12-F11,""),"") -> -2 | G13: =IFERROR(IF(AND(G12<>"",G11<>""),G12-G11,""),"") -> -4 | H13: =IFERROR(IF(AND(H12<>"",H11<>""),H12-H11,""),"") -> -7 | I13: =IFERROR(IF(AND(I12<>"",I11<>""),I12-I11,""),"") -> -8 | J13: =IFERROR(IF(AND(J12<>"",J11<>""),J12-J11,""),"") -> -10 | K13: =IFERROR(IF(AND(K12<>"",K11<>""),K12-K11,""),"") -> -14 | L13: =IFERROR(IF(AND(L12<>"",L11<>""),L12-L11,""),"") | ... X13: =IFERROR(IF(AND(X12<>"",X11<>""),X12-X11,""),"")
D14: Commentaires
A16: EXTRANTS | B16: Indicateur EXT.1 | C16: Unité / fréquence | D16: Cible | E16: 15 | F16: 28 | G16: 40 | H16: 52 | I16: 63 | J16: 72 | K16: 80 | L16: 86 | M16: 90 | N16: 93 | O16: 95 | P16: 97 | Q16: 98 | R16: 99 | S16: 100 | T16: 100 | U16: 100 | V16: 100 | W16: 100 | X16: 100
D17: Réel | E17: 12 | F17: 22 | G17: 33 | H17: 44 | I17: 56 | J17: 64 | K17: 70
D18: Déviation | E18: =IFERROR(IF(AND(E17<>"",E16<>""),E17-E16,""),"") -> -3 | F18: =IFERROR(IF(AND(F17<>"",F16<>""),F17-F16,""),"") -> -6 | G18: =IFERROR(IF(AND(G17<>"",G16<>""),G17-G16,""),"") -> -7 | H18: =IFERROR(IF(AND(H17<>"",H16<>""),H17-H16,""),"") -> -8 | I18: =IFERROR(IF(AND(I17<>"",I16<>""),I17-I16,""),"") -> -7 | J18: =IFERROR(IF(AND(J17<>"",J16<>""),J17-J16,""),"") -> -8 | K18: =IFERROR(IF(AND(K17<>"",K16<>""),K17-K16,""),"") -> -10 | L18: =IFERROR(IF(AND(L17<>"",L16<>""),L17-L16,""),"") | ... X18: =IFERROR(IF(AND(X17<>"",X16<>""),X17-X16,""),"")
D19: Commentaires

Sheet 10. Data Collection
A1: COLLECTE DE DONNÉES
A2: ⬅ MENU
A3: Projet : | D3: ='0. Profil'!C5 -> 0
A4: MÉCANISMES DE COLLECTE PAR INDICATEUR
A5: Chaîne résultats | B5: Indicateur | C5: Moyen de vérification | D5: Type données | E5: Technique collecte | F5: Valeurs mesurées | G5: Période | H5: Coût | I5: Responsable

Sheet 11. M&E Matrix
A1: MATRICE DE SUIVI & ÉVALUATION
A2: ⬅ MENU
A3: Projet : | D3: ='0. Profil'!C5 -> 0
A4: PLAN DE COMMUNICATION S&E — BESOINS INFORMATIONNELS
A5: Parties Prenantes | B5: Poids & Stratégie | C5: Besoin d'information & Indicateurs | D5: Info état initial | E5: Méthode collecte | F5: Fréquence | G5: Traitement | H5: Dissémination | I5: Motifs

Sheet 12. Disbursement Monitoring
A1: SUIVI DES DÉCAISSEMENTS & ANALYSE DE LA VALEUR ACQUISE
A2: ⬅ MENU | L2: COURBE EN S — DONNÉES CUMULÉES
A3: Projet : | D3: ='0. Profil'!C5 -> 0 | G3: Date de mise à jour : | I3: =TODAY() -> 46186 | L3: Composante | M3: CBTP Cumulé | N3: CRTR Cumulé
L4: Comp. 1 | M4: =IFERROR(SUM($C$7:C7),0) -> 850000 | N4: =IFERROR(SUM($E$7:E7),0) -> 620000
A5: No | B5: LIGNE BUDGÉTAIRE | C5: CBTP (Planifié) (1) | D5: CRTE (Engagé) (2) | E5: CRTR (Payé) (3) | F5: VARIANCES | H5: ALERT | I5: % Cons. | J5: COMMENTAIRES | L5: Comp. 2 | M5: =IFERROR(SUM($C$7:C8),0) -> 1470000 | N5: =IFERROR(SUM($E$7:E8),0) -> 1100000
F6: (1)-(2) | G6: (1)-(3) | L6: Comp. 3 | M6: =IFERROR(SUM($C$7:C9),0) -> 1890000 | N6: =IFERROR(SUM($E$7:E9),0) -> 1390000
A7: 1 | B7: Composante 1 — Personnel | C7: 850000 | D7: 750000 | E7: 620000 | F7: =IFERROR(IF(C7=0,"",C7-D7),"") -> 100000 | G7: =IFERROR(IF(C7=0,"",C7-E7),"") -> 230000 | H7: =IFERROR(IF(C7=0,"",IF(G7/C7<-0.15,"🔴 CRITIQUE",IF(G7/C7<-0.05,"🟡 ALERTE","✅ OK"))),"") -> ✅ OK | I7: =IFERROR(IF(C7=0,"",E7/C7),"") -> 0.72941176 | L7: Comp. 4 | M7: =IFERROR(SUM($C$7:C10),0) -> 2240000 | N7: =IFERROR(SUM($E$7:E10),0) -> 1630000
A8: 2 | B8: Composante 2 — Consultants | C8: 620000 | D8: 570000 | E8: 480000 | F8: =IFERROR(IF(C8=0,"",C8-D8),"") -> 50000 | G8: =IFERROR(IF(C8=0,"",C8-E8),"") -> 140000 | H8: =IFERROR(IF(C8=0,"",IF(G8/C8<-0.15,"🔴 CRITIQUE",IF(G8/C8<-0.05,"🟡 ALERTE","✅ OK"))),"") -> ✅ OK | I8: =IFERROR(IF(C8=0,"",E8/C8),"") -> 0.77419355 | L8: Comp. 5 | M8: =IFERROR(SUM($C$7:C11),0) -> 2520000 | N8: =IFERROR(SUM($E$7:E11),0) -> 1825000
A9: 3 | B9: Composante 3 — Formation | C9: 420000 | D9: 360000 | E9: 290000 | F9: =IFERROR(IF(C9=0,"",C9-D9),"") -> 60000 | G9: =IFERROR(IF(C9=0,"",C9-E9),"") -> 130000 | H9: =IFERROR(IF(C9=0,"",IF(G9/C9<-0.15,"🔴 CRITIQUE",IF(G9/C9<-0.05,"🟡 ALERTE","✅ OK"))),"") -> ✅ OK | I9: =IFERROR(IF(C9=0,"",E9/C9),"") -> 0.69047619 | L9: Comp. 6 | M9: =IFERROR(SUM($C$7:C12),0) -> 2715000 | N9: =IFERROR(SUM($E$7:E12),0) -> 1950000
A10: 4 | B10: Composante 4 — Équipements | C10: 350000 | D10: 300000 | E10: 240000 | F10: =IFERROR(IF(C10=0,"",C10-D10),"") -> 50000 | G10: =IFERROR(IF(C10=0,"",C10-E10),"") -> 110000 | H10: =IFERROR(IF(C10=0,"",IF(G10/C10<-0.15,"🔴 CRITIQUE",IF(G10/C10<-0.05,"🟡 ALERTE","✅ OK"))),"") -> ✅ OK | I10: =IFERROR(IF(C10=0,"",E10/C10),"") -> 0.68571429 | L10: Comp. 7 | M10: =IFERROR(SUM($C$7:C13),0) -> 3265000 | N10: =IFERROR(SUM($E$7:E13),0) -> 2330000
A11: 5 | B11: Composante 5 — Missions / Déplacements | C11: 280000 | D11: 240000 | E11: 195000 | F11: =IFERROR(IF(C11=0,"",C11-D11),"") -> 40000 | G11: =IFERROR(IF(C11=0,"",C11-E11),"") -> 85000 | H11: =IFERROR(IF(C11=0,"",IF(G11/C11<-0.15,"🔴 CRITIQUE",IF(G11/C11<-0.05,"🟡 ALERTE","✅ OK"))),"") -> ✅ OK | I11: =IFERROR(IF(C11=0,"",E11/C11),"") -> 0.69642857 | L11: Comp. 8 | M11: =IFERROR(SUM($C$7:C14),0) -> 3585000 | N11: =IFERROR(SUM($E$7:E14),0) -> 2540000
A12: 6 | B12: Composante 6 — Ateliers / Réunions | C12: 195000 | D12: 160000 | E12: 125000 | F12: =IFERROR(IF(C12=0,"",C12-D12),"") -> 35000 | G12: =IFERROR(IF(C12=0,"",C12-E12),"") -> 70000 | H12: =IFERROR(IF(C12=0,"",IF(G12/C12<-0.15,"🔴 CRITIQUE",IF(G12/C12<-0.05,"🟡 ALERTE","✅ OK"))),"") -> ✅ OK | I12: =IFERROR(IF(C12=0,"",E12/C12),"") -> 0.64102564 | L12: Comp. 9 | M12: =IFERROR(SUM($C$7:C15),0) -> 3735000 | N12: =IFERROR(SUM($E$7:E15),0) -> 2630000
A13: 7 | B13: Composante 7 — Infrastructures | C13: 550000 | D13: 470000 | E13: 380000 | F13: =IFERROR(IF(C13=0,"",C13-D13),"") -> 80000 | G13: =IFERROR(IF(C13=0,"",C13-E13),"") -> 170000 | H13: =IFERROR(IF(C13=0,"",IF(G13/C13<-0.15,"🔴 CRITIQUE",IF(G13/C13<-0.05,"🟡 ALERTE","✅ OK"))),"") -> ✅ OK | I13: =IFERROR(IF(C13=0,"",E13/C13),"") -> 0.69090909 | L13: Comp. 10 | M13: =IFERROR(SUM($C$7:C16),0) -> 3975000 | N13: =IFERROR(SUM($E$7:E16),0) -> 2795000
A14: 8 | B14: Composante 8 — Sous-traitance | C14: 320000 | D14: 275000 | E14: 210000 | F14: =IFERROR(IF(C14=0,"",C14-D14),"") -> 45000 | G14: =IFERROR(IF(C14=0,"",C14-E14),"") -> 110000 | H14: =IFERROR(IF(C14=0,"",IF(G14/C14<-0.15,"🔴 CRITIQUE",IF(G14/C14<-0.05,"🟡 ALERTE","✅ OK"))),"") -> ✅ OK | I14: =IFERROR(IF(C14=0,"",E14/C14),"") -> 0.65625 | L14: Comp. 11 | M14: =IFERROR(SUM($C$7:C17),0) -> 4155000 | N14: =IFERROR(SUM($E$7:E17),0) -> 2905000
A15: 9 | B15: Composante 9 — Communication | C15: 150000 | D15: 120000 | E15: 90000 | F15: =IFERROR(IF(C15=0,"",C15-D15),"") -> 30000 | G15: =IFERROR(IF(C15=0,"",C15-E15),"") -> 60000 | H15: =IFERROR(IF(C15=0,"",IF(G15/C15<-0.15,"🔴 CRITIQUE",IF(G15/C15<-0.05,"🟡 ALERTE","✅ OK"))),"") -> ✅ OK | I15: =IFERROR(IF(C15=0,"",E15/C15),"") -> 0.6 | L15: Comp. 12 | M15: =IFERROR(SUM($C$7:C18),0) -> 4275000 | N15: =IFERROR(SUM($E$7:E18),0) -> 2985000
A16: 10 | B16: Composante 10 — Frais généraux | C16: 240000 | D16: 210000 | E16: 165000 | F16: =IFERROR(IF(C16=0,"",C16-D16),"") -> 30000 | G16: =IFERROR(IF(C16=0,"",C16-E16),"") -> 75000 | H16: =IFERROR(IF(C16=0,"",IF(G16/C16<-0.15,"🔴 CRITIQUE",IF(G16/C16<-0.05,"🟡 ALERTE","✅ OK"))),"") -> ✅ OK | I16: =IFERROR(IF(C16=0,"",E16/C16),"") -> 0.6875 | L16: Comp. 13 | M16: =IFERROR(SUM($C$7:C19),0) -> 4370000 | N16: =IFERROR(SUM($E$7:E19),0) -> 3050000
A17: 11 | B17: Composante 11 — Imprévus | C17: 180000 | D17: 145000 | E17: 110000 | F17: =IFERROR(IF(C17=0,"",C17-D17),"") -> 35000 | G17: =IFERROR(IF(C17=0,"",C17-E17),"") -> 70000 | H17: =IFERROR(IF(C17=0,"",IF(G17/C17<-0.15,"🔴 CRITIQUE",IF(G17/C17<-0.05,"🟡 ALERTE","✅ OK"))),"") -> ✅ OK | I17: =IFERROR(IF(C17=0,"",E17/C17),"") -> 0.61111111 | L17: Comp. 14 | M17: =IFERROR(SUM($C$7:C20),0) -> 4680000 | N17: =IFERROR(SUM($E$7:E20),0) -> 3260000
A18: 12 | B18: Composante 12 — Évaluation | C18: 120000 | D18: 100000 | E18: 80000 | F18: =IFERROR(IF(C18=0,"",C18-D18),"") -> 20000 | G18: =IFERROR(IF(C18=0,"",C18-E18),"") -> 40000 | H18: =IFERROR(IF(C18=0,"",IF(G18/C18<-0.15,"🔴 CRITIQUE",IF(G18/C18<-0.05,"🟡 ALERTE","✅ OK"))),"") -> ✅ OK | I18: =IFERROR(IF(C18=0,"",E18/C18),"") -> 0.66666667 | L18: Comp. 15 | M18: =IFERROR(SUM($C$7:C21),0) -> 4830000 | N18: =IFERROR(SUM($E$7:E21),0) -> 3355000
A19: 13 | B19: Composante 13 — Audit | C19: 95000 | D19: 80000 | E19: 65000 | F19: =IFERROR(IF(C19=0,"",C19-D19),"") -> 15000 | G19: =IFERROR(IF(C19=0,"",C19-E19),"") -> 30000 | H19: =IFERROR(IF(C19=0,"",IF(G19/C19<-0.15,"🔴 CRITIQUE",IF(G19/C19<-0.05,"🟡 ALERTE","✅ OK"))),"") -> ✅ OK | I19: =IFERROR(IF(C19=0,"",E19/C19),"") -> 0.68421053
A20: 14 | B20: Composante 14 — Gestion du projet | C20: 310000 | D20: 260000 | E20: 210000 | F20: =IFERROR(IF(C20=0,"",C20-D20),"") -> 50000 | G20: =IFERROR(IF(C20=0,"",C20-E20),"") -> 100000 | H20: =IFERROR(IF(C20=0,"",IF(G20/C20<-0.15,"🔴 CRITIQUE",IF(G20/C20<-0.05,"🟡 ALERTE","✅ OK"))),"") -> ✅ OK | I20: =IFERROR(IF(C20=0,"",E20/C20),"") -> 0.67741935
A21: 15 | B21: Composante 15 — Autres | C21: 150000 | D21: 125000 | E21: 95000 | F21: =IFERROR(IF(C21=0,"",C21-D21),"") -> 25000 | G21: =IFERROR(IF(C21=0,"",C21-E21),"") -> 55000 | H21: =IFERROR(IF(C21=0,"",IF(G21/C21<-0.15,"🔴 CRITIQUE",IF(G21/C21<-0.05,"🟡 ALERTE","✅ OK"))),"") -> ✅ OK | I21: =IFERROR(IF(C21=0,"",E21/C21),"") -> 0.63333333
A23: TOTAUX | C23: =SUM(C7:C21) -> 4830000 | D23: =SUM(D7:D21) -> 4165000 | E23: =SUM(E7:E21) -> 3355000 | F23: =C23-D23 -> 665000 | G23: =C23-E23 -> 1475000 | I23: =IFERROR(E23/C23,"") -> 0.69461698

Sheet 13. Dashboard
A1: 🎯 TABLEAU DE BORD — ANALYSE DE LA VALEUR ACQUISE (EVM)
A2: ⬅ MENU
A3: Projet : | D3: ='0. Profil'!C5 -> 0 | H3: Responsable : | K3: ='0. Profil'!C7 -> 0 | N3: =TODAY() -> 46186
A5: INDICATEURS CLÉS DE PERFORMANCE (EVM)
A6: COÛT BUDGÉTÉ DU PROJET (Budget Total) | C6: ='0. Profil'!C17 -> 0 | D6: Budget saisi dans 0. Profil
A7: CBTP — Valeur Planifiée (PV) | C7: ='12. Disbursement Monitoring'!C23 -> 4830000 | D7: Total planifié onglet 12
A8: CRTR — Coût Réel (AC) | C8: ='12. Disbursement Monitoring'!E23 -> 3355000 | D8: Total payé onglet 12
A9: % TRAVAIL EFFECTUÉ (saisir manuellement) | C9: 0.14 | D9: INPUT — % physique d'avancement
A10: CBTE — Valeur Acquise (EV) | C10: =IFERROR(C6*C9,"") -> 0 | D10: Budget × % travail
A11: VARIATION SUR LES COÛTS (CV = EV - AC) | C11: =IFERROR(C10-C8,"") -> -3355000 | D11: Positif = sous budget
A12: INDICE PERF. COÛTS — IPC (CPI = EV/AC) | C12: =IFERROR(C10/C8,"") -> 0 | D12: IPC > 1 = sous budget
A13: VARIATION ÉCHÉANCIER (SV = EV - PV) | C13: =IFERROR(C10-C7,"") -> -4830000 | D13: Positif = en avance
A14: INDICE PERF. ÉCHÉANCIER — IPE (SPI = EV/PV) | C14: =IFERROR(C10/C7,"") -> 0 | D14: IPE > 1 = en avance
A15: EAC — Estimé à l'Achèvement (Budget/IPC) | C15: =IFERROR(C6/C12,"") | D15: Projection coût final
A16: VAC — Variance à l'Achèvement (Budget - EAC) | C16: =IFERROR(C6-C15,"") | D16: Positif = économies prévues
A17: TCPI — Indice Perf. Restante (Reste/Budget restant) | C17: =IFERROR((C6-C10)/(C6-C8),"") -> 0 | D17: TCPI < 1 = objectif atteignable
A19: STATUT GLOBAL DU PROJET
A20: STATUT COÛTS (IPC) | D20: =IFERROR(IF(C12>=1,"✅ SOUS BUDGET",IF(C12>=0.85,"⚠️ ATTENTION","🔴 DÉPASSEMENT")),"N/A") -> 🔴 DÉPASSEMENT
A21: STATUT CALENDRIER (IPE) | D21: =IFERROR(IF(C14>=1,"✅ EN AVANCE",IF(C14>=0.9,"⚠️ LÉGER RETARD","🔴 RETARD CRITIQUE")),"N/A") -> 🔴 RETARD CRITIQUE
A22: STATUT GLOBAL PROJET | D22: =IFERROR(IF(AND(C12>=0.9,C14>=0.9),"🟢 VERT — Projet sous contrôle",IF(AND(C12>=0.75,C14>=0.75),"🟡 AMBRE — Surveillance requise","🔴 ROUGE — Action corrective urgente")),"N/A") -> 🔴 ROUGE — Action corrective urgente
A24: SYNTHÈSE RISQUES (depuis onglet 5)
A25: 🔴 Risques CRITIQUES | C25: ='5. Risks Analysis'!H19 -> 1
A26: 🟠 Risques ÉLEVÉS | C26: ='5. Risks Analysis'!H20 -> 6
A27: 🟡 Risques MODÉRÉS | C27: ='5. Risks Analysis'!H21 -> 3
A28: Score moyen risques | C28: ='5. Risks Analysis'!H23 -> 10.2
C29: =IFERROR(IF(AND(C12>=0.9,C14>=0.9),"🟢 VERT",IF(AND(C12>=0.75,C14>=0.75),"🟡 AMBRE","🔴 ROUGE")),"N/A") -> 🔴 ROUGE
A32: 📊 VISUALISATIONS DYNAMIQUES
R33: Indice | S33: Valeur | T33: Seuil
R34: IPC | S34: =C12 -> 0 | T34: 1
R35: IPE | S35: =C14 -> 0 | T35: 1
R36: TCPI | S36: =C17 -> 0 | T36: 1

Sheet 14. Status report
A1: RAPPORT D'AVANCEMENT DU PROJET
A2: ⬅ MENU
A3: INFORMATIONS GÉNÉRALES
B4: Projet :
B5: Période du rapport :
B6: Responsable du suivi :
A8: 1. OBJECTIF DU PROJET
A10: 2. COMMENTAIRES GÉNÉRAUX
A14: 3. ÉTAT D'AVANCEMENT EXTRANTS
A18: 4. ANALYSE DES DÉVIATIONS
A22: 4.1 PERFORMANCE CALENDRIER (IPE)
B23: IPE (depuis Dashboard) : | C23: ='13. Dashboard'!C14 -> 0
B24: Retard en jours :
A26: 4.2 PERFORMANCE COÛTS (IPC)
B27: IPC (depuis Dashboard) : | C27: ='13. Dashboard'!C12 -> 0
B28: EAC (depuis Dashboard) : | C28: ='13. Dashboard'!C15
A30: 5. PASSATION DE MARCHÉS
B31: DAO | C31: Date planifiée | D31: Date réelle | E31: Signature planifiée | F31: Signature réelle
A34: 6. RECOMMANDATIONS
A38: 7. ANNEXES

Sheet 15. Evaluation Matrix
A1: MATRICE D'ÉVALUATION
A2: ⬅ MENU
A3: Projet : | D3: ='0. Profil'!C5 -> 0
A4: FOCUS ÉVALUATION — CRITÈRES DAC & CYCLE DE PROJET
A5: Chaîne de résultats | B5: Indicateurs | C5: Pertinence | D5: Efficacité | E5: Efficience | F5: Effet | G5: Impact | H5: Questions d'évaluation | I5: Phase du projet

Sheet 16. Procurement Plan
A1: PLAN DE PASSATION DES MARCHÉS
A2: ⬅ MENU
A3: Projet : | D3: ='0. Profil'!C5 -> 0
A4: SUIVI DES ACQUISITIONS ET CONTRATS
A5: No | B5: Description | C5: Nb Lots | D5: Date soumission PTF | E5: Approbation PT&F | F5: Référence doc | G5: Date soumission PPM | H5: Non-objection bailleurs | I5: PPM approuvé Ministre | J5: Date | K5: Lettre référence
